bovine_pubsub/__init__.py
bovine_pubsub/amqp.py
bovine_pubsub/amqp_iterator.py
bovine_pubsub/amqp_manager.py
bovine_pubsub/queue.py
bovine_pubsub/redis.py
bovine_pubsub/test_app.py
bovine_pubsub-0.5.19.dist-info/METADATA
bovine_pubsub-0.5.19.dist-info/WHEEL
bovine_pubsub-0.5.19.dist-info/RECORD
