Metadata-Version: 2.1
Name: bovine-pubsub
Version: 0.5.19
Summary: A Quart thing to handle pubsub tasks in particular the event source
Home-page: https://codeberg.org/bovine/bovine
License: MIT
Author: Helge
Author-email: helge.krueger@gmail.com
Requires-Python: >=3.11,<4.0
Classifier: License :: OSI Approved :: MIT License
Classifier: Programming Language :: Python :: 3
Classifier: Programming Language :: Python :: 3.11
Requires-Dist: aio-pika (>=9.2.2,<10.0.0)
Requires-Dist: bovine (>=0.5.19,<0.6.0)
Requires-Dist: quart-redis (>=2.0.0,<3.0.0)
Project-URL: Repository, https://codeberg.org/bovine/bovine
